odoo/addons/sale_order_split_strategy/README.rst
odoo/addons/sale_order_split_strategy/__init__.py
odoo/addons/sale_order_split_strategy/__manifest__.py
odoo/addons/sale_order_split_strategy/i18n/it.po
odoo/addons/sale_order_split_strategy/i18n/pt.po
odoo/addons/sale_order_split_strategy/i18n/sale_order_split_strategy.pot
odoo/addons/sale_order_split_strategy/models/__init__.py
odoo/addons/sale_order_split_strategy/models/res_company.py
odoo/addons/sale_order_split_strategy/models/res_config.py
odoo/addons/sale_order_split_strategy/models/sale_order.py
odoo/addons/sale_order_split_strategy/models/sale_order_split_strategy.py
odoo/addons/sale_order_split_strategy/readme/CONSTRIBUTORS.rst
odoo/addons/sale_order_split_strategy/readme/DESCRIPTION.md
odoo/addons/sale_order_split_strategy/readme/USAGE.md
odoo/addons/sale_order_split_strategy/security/ir.model.access.csv
odoo/addons/sale_order_split_strategy/static/description/icon.png
odoo/addons/sale_order_split_strategy/static/description/index.html
odoo/addons/sale_order_split_strategy/tests/__init__.py
odoo/addons/sale_order_split_strategy/tests/test_split_strategy.py
odoo/addons/sale_order_split_strategy/views/mail_message_template.xml
odoo/addons/sale_order_split_strategy/views/res_config.xml
odoo/addons/sale_order_split_strategy/views/sale_order.xml
odoo/addons/sale_order_split_strategy/views/sale_order_split_strategy.xml
odoo_addon_sale_order_split_strategy-18.0.1.1.0.2.dist-info/METADATA
odoo_addon_sale_order_split_strategy-18.0.1.1.0.2.dist-info/WHEEL
odoo_addon_sale_order_split_strategy-18.0.1.1.0.2.dist-info/top_level.txt
odoo_addon_sale_order_split_strategy-18.0.1.1.0.2.dist-info/RECORD
